Workbook

Sheet 00_INICIO
A1: CARNE PREMIUM ERP
A2: MVP 0.1.5
A4: Flujo | B4: Cliente → Producto → Kg → Motor Comercial → Precio → Venta
A5: Paso 1 | B5: Escribir nombre del cliente
A6: Paso 2 | B6: Escribir nombre del producto
A7: Paso 3 | B7: Cargar Kg
A8: Paso 4 | B8: El motor determina el precio
A9: Paso 5 | B9: Verificar precio aplicado y motivo
A10: Estado | B10: MVP 0.1.5
A11: Compatibilidad | B11: Excel 2019 + Google Sheets

Sheet 01_PARAMETROS
A1: Parametro | B1: Valor
A2: Empresa | B2: Carne Premium
A3: Moneda | B3: ARS
A4: TipoPrecioDefault | B4: Minorista
A5: MedioPagoDefault | B5: Efectivo
A6: IVA | B6: 21

Sheet 02_CATALOGOS
A1: TiposPrecio | B1: TiposCliente | C1: MediosPago | D1: Estados
A2: Minorista | B2: Minorista | C2: Efectivo | D2: Activo
A3: Mayorista | B3: Mayorista | C3: Transferencia | D3: Inactivo
A4: Especial | B4: Especial | C4: Cuenta Corriente
C5: Tarjeta
C6: Otro

Sheet 03_CLIENTES
A1: ClienteID | B1: Nombre | C1: Telefono | D1: Direccion | E1: TipoCliente | F1: Estado | G1: Observaciones
A2: =IF(B2="","","CLI"&TEXT(ROW()-1,"000000")) | F2: Activo
A3: =IF(B3="","","CLI"&TEXT(ROW()-1,"000000")) | F3: Activo
A4: =IF(B4="","","CLI"&TEXT(ROW()-1,"000000")) | F4: Activo
A5: =IF(B5="","","CLI"&TEXT(ROW()-1,"000000")) | F5: Activo
A6: =IF(B6="","","CLI"&TEXT(ROW()-1,"000000")) | F6: Activo
A7: =IF(B7="","","CLI"&TEXT(ROW()-1,"000000")) | F7: Activo
A8: =IF(B8="","","CLI"&TEXT(ROW()-1,"000000")) | F8: Activo
A9: =IF(B9="","","CLI"&TEXT(ROW()-1,"000000")) | F9: Activo
A10: =IF(B10="","","CLI"&TEXT(ROW()-1,"000000")) | F10: Activo
A11: =IF(B11="","","CLI"&TEXT(ROW()-1,"000000")) | F11: Activo
A12: =IF(B12="","","CLI"&TEXT(ROW()-1,"000000")) | F12: Activo
A13: =IF(B13="","","CLI"&TEXT(ROW()-1,"000000")) | F13: Activo
... A500: =IF(B500="","","CLI"&TEXT(ROW()-1,"000000")) | F500: Activo

Sheet 04_PRODUCTOS
A1: ProductoID | B1: Producto | C1: Categoria | D1: Costo | E1: PrecioMinorista | F1: PrecioMayorista | G1: PrecioEspecial | H1: Estado | I1: Observaciones
A2: =IF(B2="","","PRO"&TEXT(ROW()-1,"000000")) | H2: Activo
A3: =IF(B3="","","PRO"&TEXT(ROW()-1,"000000")) | H3: Activo
A4: =IF(B4="","","PRO"&TEXT(ROW()-1,"000000")) | H4: Activo
A5: =IF(B5="","","PRO"&TEXT(ROW()-1,"000000")) | H5: Activo
A6: =IF(B6="","","PRO"&TEXT(ROW()-1,"000000")) | H6: Activo
A7: =IF(B7="","","PRO"&TEXT(ROW()-1,"000000")) | H7: Activo
A8: =IF(B8="","","PRO"&TEXT(ROW()-1,"000000")) | H8: Activo
A9: =IF(B9="","","PRO"&TEXT(ROW()-1,"000000")) | H9: Activo
A10: =IF(B10="","","PRO"&TEXT(ROW()-1,"000000")) | H10: Activo
A11: =IF(B11="","","PRO"&TEXT(ROW()-1,"000000")) | H11: Activo
A12: =IF(B12="","","PRO"&TEXT(ROW()-1,"000000")) | H12: Activo
A13: =IF(B13="","","PRO"&TEXT(ROW()-1,"000000")) | H13: Activo
... A500: =IF(B500="","","PRO"&TEXT(ROW()-1,"000000")) | H500: Activo

Sheet 05_VENTAS
A1: VentaID | B1: Fecha | C1: Hora | D1: Cliente | E1: TipoPrecio | F1: Producto | G1: Kg | H1: PrecioKg | I1: Importe | J1: Ganancia$ | K1: Ganancia% | L1: MedioPago | M1: Vendedor | N1: Observaciones | O1: _ClienteID | P1: _ProductoID | Q1: EstadoVenta | R1: TipoAplicado | S1: MotivoPrecio | T1: OfertaID | U1: OfertaNombre
A2: =IF(OR(D2="",F2=""),"","VEN"&TEXT(ROW()-1,"000000")) | B2: =IF(A2="","",TODAY()) | C2: =IF(A2="","",NOW()) | H2: =IFERROR(IF(E2="Mayorista",IF(INDEX('04_PRODUCTOS'!$F$2:$F$501,MATCH(F2,'04_PRODUCTOS'!$B$2:$B$501,0))="",INDEX('04_PRODUCTOS'!$E$2:$E$501,MATCH(F2,'04_PRODUCTOS'!$B$2:$B$501,0)),INDEX('04_PRODUCTOS'!$F$2:$F$501,MATCH(F2,'04_PRODUCTOS'!$B$2:$B$501,0))),IF(E2="Especial",IF(INDEX('04_PRODUCTOS'!$G$2:$G$501,MATCH(F2,'04_PRODUCTOS'!$B$2:$B$501,0))="",INDEX('04_PRODUCTOS'!$E$2:$E$501,MATCH(F2,'04_PRODUCTOS'!$B$2:$B$501,0)),INDEX('04_PRODUCTOS'!$G$2:$G$501,MATCH(F2,'04_PRODUCTOS'!$B$2:$B$501,0))),INDEX('04_PRODUCTOS'!$E$2:$E$501,MATCH(F2,'04_PRODUCTOS'!$B$2:$B$501,0)))),"") | I2: =IF(AND(G2<>"",H2<>""),G2*H2,"") | J2: =IFERROR(IF(INDEX('04_PRODUCTOS'!$D$2:$D$501,MATCH(F2,'04_PRODUCTOS'!$B$2:$B$501,0))="","",I2-(G2*INDEX('04_PRODUCTOS'!$D$2:$D$501,MATCH(F2,'04_PRODUCTOS'!$B$2:$B$501,0)))),"") | K2: =IF(OR(I2="",J2=""),"",IFERROR(J2/I2,"")) | O2: =IF(D2="","",IFERROR(INDEX('03_CLIENTES'!$A$2:$A$501,MATCH(D2,'03_CLIENTES'!$B$2:$B$501,0)),"")) | P2: =IF(F2="","",IFERROR(INDEX('04_PRODUCTOS'!$A$2:$A$501,MATCH(F2,'04_PRODUCTOS'!$B$2:$B$501,0)),"")) | Q2: =IF(AND(D2<>"",F2<>"",G2>0,H2<>""),IF(O2="","CLIENTE NO ENCONTRADO",IF(P2="","PRODUCTO NO ENCONTRADO","OK")),"")
A3: =IF(OR(D3="",F3=""),"","VEN"&TEXT(ROW()-1,"000000")) | B3: =IF(A3="","",TODAY()) | C3: =IF(A3="","",NOW()) | H3: =IFERROR(IF(E3="Mayorista",IF(INDEX('04_PRODUCTOS'!$F$2:$F$501,MATCH(F3,'04_PRODUCTOS'!$B$2:$B$501,0))="",INDEX('04_PRODUCTOS'!$E$2:$E$501,MATCH(F3,'04_PRODUCTOS'!$B$2:$B$501,0)),INDEX('04_PRODUCTOS'!$F$2:$F$501,MATCH(F3,'04_PRODUCTOS'!$B$2:$B$501,0))),IF(E3="Especial",IF(INDEX('04_PRODUCTOS'!$G$2:$G$501,MATCH(F3,'04_PRODUCTOS'!$B$2:$B$501,0))="",INDEX('04_PRODUCTOS'!$E$2:$E$501,MATCH(F3,'04_PRODUCTOS'!$B$2:$B$501,0)),INDEX('04_PRODUCTOS'!$G$2:$G$501,MATCH(F3,'04_PRODUCTOS'!$B$2:$B$501,0))),INDEX('04_PRODUCTOS'!$E$2:$E$501,MATCH(F3,'04_PRODUCTOS'!$B$2:$B$501,0)))),"") | I3: =IF(AND(G3<>"",H3<>""),G3*H3,"") | J3: =IFERROR(IF(INDEX('04_PRODUCTOS'!$D$2:$D$501,MATCH(F3,'04_PRODUCTOS'!$B$2:$B$501,0))="","",I3-(G3*INDEX('04_PRODUCTOS'!$D$2:$D$501,MATCH(F3,'04_PRODUCTOS'!$B$2:$B$501,0)))),"") | K3: =IF(OR(I3="",J3=""),"",IFERROR(J3/I3,"")) | O3: =IF(D3="","",IFERROR(INDEX('03_CLIENTES'!$A$2:$A$501,MATCH(D3,'03_CLIENTES'!$B$2:$B$501,0)),"")) | P3: =IF(F3="","",IFERROR(INDEX('04_PRODUCTOS'!$A$2:$A$501,MATCH(F3,'04_PRODUCTOS'!$B$2:$B$501,0)),"")) | Q3: =IF(AND(D3<>"",F3<>"",G3>0,H3<>""),IF(O3="","CLIENTE NO ENCONTRADO",IF(P3="","PRODUCTO NO ENCONTRADO","OK")),"")
A4: =IF(OR(D4="",F4=""),"","VEN"&TEXT(ROW()-1,"000000")) | B4: =IF(A4="","",TODAY()) | C4: =IF(A4="","",NOW()) | H4: =IFERROR(IF(E4="Mayorista",IF(INDEX('04_PRODUCTOS'!$F$2:$F$501,MATCH(F4,'04_PRODUCTOS'!$B$2:$B$501,0))="",INDEX('04_PRODUCTOS'!$E$2:$E$501,MATCH(F4,'04_PRODUCTOS'!$B$2:$B$501,0)),INDEX('04_PRODUCTOS'!$F$2:$F$501,MATCH(F4,'04_PRODUCTOS'!$B$2:$B$501,0))),IF(E4="Especial",IF(INDEX('04_PRODUCTOS'!$G$2:$G$501,MATCH(F4,'04_PRODUCTOS'!$B$2:$B$501,0))="",INDEX('04_PRODUCTOS'!$E$2:$E$501,MATCH(F4,'04_PRODUCTOS'!$B$2:$B$501,0)),INDEX('04_PRODUCTOS'!$G$2:$G$501,MATCH(F4,'04_PRODUCTOS'!$B$2:$B$501,0))),INDEX('04_PRODUCTOS'!$E$2:$E$501,MATCH(F4,'04_PRODUCTOS'!$B$2:$B$501,0)))),"") | I4: =IF(AND(G4<>"",H4<>""),G4*H4,"") | J4: =IFERROR(IF(INDEX('04_PRODUCTOS'!$D$2:$D$501,MATCH(F4,'04_PRODUCTOS'!$B$2:$B$501,0))="","",I4-(G4*INDEX('04_PRODUCTOS'!$D$2:$D$501,MATCH(F4,'04_PRODUCTOS'!$B$2:$B$501,0)))),"") | K4: =IF(OR(I4="",J4=""),"",IFERROR(J4/I4,"")) | O4: =IF(D4="","",IFERROR(INDEX('03_CLIENTES'!$A$2:$A$501,MATCH(D4,'03_CLIENTES'!$B$2:$B$501,0)),"")) | P4: =IF(F4="","",IFERROR(INDEX('04_PRODUCTOS'!$A$2:$A$501,MATCH(F4,'04_PRODUCTOS'!$B$2:$B$501,0)),"")) | Q4: =IF(AND(D4<>"",F4<>"",G4>0,H4<>""),IF(O4="","CLIENTE NO ENCONTRADO",IF(P4="","PRODUCTO NO ENCONTRADO","OK")),"")
A5: =IF(OR(D5="",F5=""),"","VEN"&TEXT(ROW()-1,"000000")) | B5: =IF(A5="","",TODAY()) | C5: =IF(A5="","",NOW()) | H5: =IFERROR(IF(E5="Mayorista",IF(INDEX('04_PRODUCTOS'!$F$2:$F$501,MATCH(F5,'04_PRODUCTOS'!$B$2:$B$501,0))="",INDEX('04_PRODUCTOS'!$E$2:$E$501,MATCH(F5,'04_PRODUCTOS'!$B$2:$B$501,0)),INDEX('04_PRODUCTOS'!$F$2:$F$501,MATCH(F5,'04_PRODUCTOS'!$B$2:$B$501,0))),IF(E5="Especial",IF(INDEX('04_PRODUCTOS'!$G$2:$G$501,MATCH(F5,'04_PRODUCTOS'!$B$2:$B$501,0))="",INDEX('04_PRODUCTOS'!$E$2:$E$501,MATCH(F5,'04_PRODUCTOS'!$B$2:$B$501,0)),INDEX('04_PRODUCTOS'!$G$2:$G$501,MATCH(F5,'04_PRODUCTOS'!$B$2:$B$501,0))),INDEX('04_PRODUCTOS'!$E$2:$E$501,MATCH(F5,'04_PRODUCTOS'!$B$2:$B$501,0)))),"") | I5: =IF(AND(G5<>"",H5<>""),G5*H5,"") | J5: =IFERROR(IF(INDEX('04_PRODUCTOS'!$D$2:$D$501,MATCH(F5,'04_PRODUCTOS'!$B$2:$B$501,0))="","",I5-(G5*INDEX('04_PRODUCTOS'!$D$2:$D$501,MATCH(F5,'04_PRODUCTOS'!$B$2:$B$501,0)))),"") | K5: =IF(OR(I5="",J5=""),"",IFERROR(J5/I5,"")) | O5: =IF(D5="","",IFERROR(INDEX('03_CLIENTES'!$A$2:$A$501,MATCH(D5,'03_CLIENTES'!$B$2:$B$501,0)),"")) | P5: =IF(F5="","",IFERROR(INDEX('04_PRODUCTOS'!$A$2:$A$501,MATCH(F5,'04_PRODUCTOS'!$B$2:$B$501,0)),"")) | Q5: =IF(AND(D5<>"",F5<>"",G5>0,H5<>""),IF(O5="","CLIENTE NO ENCONTRADO",IF(P5="","PRODUCTO NO ENCONTRADO","OK")),"")
A6: =IF(OR(D6="",F6=""),"","VEN"&TEXT(ROW()-1,"000000")) | B6: =IF(A6="","",TODAY()) | C6: =IF(A6="","",NOW()) | H6: =IFERROR(IF(E6="Mayorista",IF(INDEX('04_PRODUCTOS'!$F$2:$F$501,MATCH(F6,'04_PRODUCTOS'!$B$2:$B$501,0))="",INDEX('04_PRODUCTOS'!$E$2:$E$501,MATCH(F6,'04_PRODUCTOS'!$B$2:$B$501,0)),INDEX('04_PRODUCTOS'!$F$2:$F$501,MATCH(F6,'04_PRODUCTOS'!$B$2:$B$501,0))),IF(E6="Especial",IF(INDEX('04_PRODUCTOS'!$G$2:$G$501,MATCH(F6,'04_PRODUCTOS'!$B$2:$B$501,0))="",INDEX('04_PRODUCTOS'!$E$2:$E$501,MATCH(F6,'04_PRODUCTOS'!$B$2:$B$501,0)),INDEX('04_PRODUCTOS'!$G$2:$G$501,MATCH(F6,'04_PRODUCTOS'!$B$2:$B$501,0))),INDEX('04_PRODUCTOS'!$E$2:$E$501,MATCH(F6,'04_PRODUCTOS'!$B$2:$B$501,0)))),"") | I6: =IF(AND(G6<>"",H6<>""),G6*H6,"") | J6: =IFERROR(IF(INDEX('04_PRODUCTOS'!$D$2:$D$501,MATCH(F6,'04_PRODUCTOS'!$B$2:$B$501,0))="","",I6-(G6*INDEX('04_PRODUCTOS'!$D$2:$D$501,MATCH(F6,'04_PRODUCTOS'!$B$2:$B$501,0)))),"") | K6: =IF(OR(I6="",J6=""),"",IFERROR(J6/I6,"")) | O6: =IF(D6="","",IFERROR(INDEX('03_CLIENTES'!$A$2:$A$501,MATCH(D6,'03_CLIENTES'!$B$2:$B$501,0)),"")) | P6: =IF(F6="","",IFERROR(INDEX('04_PRODUCTOS'!$A$2:$A$501,MATCH(F6,'04_PRODUCTOS'!$B$2:$B$501,0)),"")) | Q6: =IF(AND(D6<>"",F6<>"",G6>0,H6<>""),IF(O6="","CLIENTE NO ENCONTRADO",IF(P6="","PRODUCTO NO ENCONTRADO","OK")),"")
A7: =IF(OR(D7="",F7=""),"","VEN"&TEXT(ROW()-1,"000000")) | B7: =IF(A7="","",TODAY()) | C7: =IF(A7="","",NOW()) | H7: =IFERROR(IF(E7="Mayorista",IF(INDEX('04_PRODUCTOS'!$F$2:$F$501,MATCH(F7,'04_PRODUCTOS'!$B$2:$B$501,0))="",INDEX('04_PRODUCTOS'!$E$2:$E$501,MATCH(F7,'04_PRODUCTOS'!$B$2:$B$501,0)),INDEX('04_PRODUCTOS'!$F$2:$F$501,MATCH(F7,'04_PRODUCTOS'!$B$2:$B$501,0))),IF(E7="Especial",IF(INDEX('04_PRODUCTOS'!$G$2:$G$501,MATCH(F7,'04_PRODUCTOS'!$B$2:$B$501,0))="",INDEX('04_PRODUCTOS'!$E$2:$E$501,MATCH(F7,'04_PRODUCTOS'!$B$2:$B$501,0)),INDEX('04_PRODUCTOS'!$G$2:$G$501,MATCH(F7,'04_PRODUCTOS'!$B$2:$B$501,0))),INDEX('04_PRODUCTOS'!$E$2:$E$501,MATCH(F7,'04_PRODUCTOS'!$B$2:$B$501,0)))),"") | I7: =IF(AND(G7<>"",H7<>""),G7*H7,"") | J7: =IFERROR(IF(INDEX('04_PRODUCTOS'!$D$2:$D$501,MATCH(F7,'04_PRODUCTOS'!$B$2:$B$501,0))="","",I7-(G7*INDEX('04_PRODUCTOS'!$D$2:$D$501,MATCH(F7,'04_PRODUCTOS'!$B$2:$B$501,0)))),"") | K7: =IF(OR(I7="",J7=""),"",IFERROR(J7/I7,"")) | O7: =IF(D7="","",IFERROR(INDEX('03_CLIENTES'!$A$2:$A$501,MATCH(D7,'03_CLIENTES'!$B$2:$B$501,0)),"")) | P7: =IF(F7="","",IFERROR(INDEX('04_PRODUCTOS'!$A$2:$A$501,MATCH(F7,'04_PRODUCTOS'!$B$2:$B$501,0)),"")) | Q7: =IF(AND(D7<>"",F7<>"",G7>0,H7<>""),IF(O7="","CLIENTE NO ENCONTRADO",IF(P7="","PRODUCTO NO ENCONTRADO","OK")),"")
A8: =IF(OR(D8="",F8=""),"","VEN"&TEXT(ROW()-1,"000000")) | B8: =IF(A8="","",TODAY()) | C8: =IF(A8="","",NOW()) | H8: =IFERROR(IF(E8="Mayorista",IF(INDEX('04_PRODUCTOS'!$F$2:$F$501,MATCH(F8,'04_PRODUCTOS'!$B$2:$B$501,0))="",INDEX('04_PRODUCTOS'!$E$2:$E$501,MATCH(F8,'04_PRODUCTOS'!$B$2:$B$501,0)),INDEX('04_PRODUCTOS'!$F$2:$F$501,MATCH(F8,'04_PRODUCTOS'!$B$2:$B$501,0))),IF(E8="Especial",IF(INDEX('04_PRODUCTOS'!$G$2:$G$501,MATCH(F8,'04_PRODUCTOS'!$B$2:$B$501,0))="",INDEX('04_PRODUCTOS'!$E$2:$E$501,MATCH(F8,'04_PRODUCTOS'!$B$2:$B$501,0)),INDEX('04_PRODUCTOS'!$G$2:$G$501,MATCH(F8,'04_PRODUCTOS'!$B$2:$B$501,0))),INDEX('04_PRODUCTOS'!$E$2:$E$501,MATCH(F8,'04_PRODUCTOS'!$B$2:$B$501,0)))),"") | I8: =IF(AND(G8<>"",H8<>""),G8*H8,"") | J8: =IFERROR(IF(INDEX('04_PRODUCTOS'!$D$2:$D$501,MATCH(F8,'04_PRODUCTOS'!$B$2:$B$501,0))="","",I8-(G8*INDEX('04_PRODUCTOS'!$D$2:$D$501,MATCH(F8,'04_PRODUCTOS'!$B$2:$B$501,0)))),"") | K8: =IF(OR(I8="",J8=""),"",IFERROR(J8/I8,"")) | O8: =IF(D8="","",IFERROR(INDEX('03_CLIENTES'!$A$2:$A$501,MATCH(D8,'03_CLIENTES'!$B$2:$B$501,0)),"")) | P8: =IF(F8="","",IFERROR(INDEX('04_PRODUCTOS'!$A$2:$A$501,MATCH(F8,'04_PRODUCTOS'!$B$2:$B$501,0)),"")) | Q8: =IF(AND(D8<>"",F8<>"",G8>0,H8<>""),IF(O8="","CLIENTE NO ENCONTRADO",IF(P8="","PRODUCTO NO ENCONTRADO","OK")),"")
A9: =IF(OR(D9="",F9=""),"","VEN"&TEXT(ROW()-1,"000000")) | B9: =IF(A9="","",TODAY()) | C9: =IF(A9="","",NOW()) | H9: =IFERROR(IF(E9="Mayorista",IF(INDEX('04_PRODUCTOS'!$F$2:$F$501,MATCH(F9,'04_PRODUCTOS'!$B$2:$B$501,0))="",INDEX('04_PRODUCTOS'!$E$2:$E$501,MATCH(F9,'04_PRODUCTOS'!$B$2:$B$501,0)),INDEX('04_PRODUCTOS'!$F$2:$F$501,MATCH(F9,'04_PRODUCTOS'!$B$2:$B$501,0))),IF(E9="Especial",IF(INDEX('04_PRODUCTOS'!$G$2:$G$501,MATCH(F9,'04_PRODUCTOS'!$B$2:$B$501,0))="",INDEX('04_PRODUCTOS'!$E$2:$E$501,MATCH(F9,'04_PRODUCTOS'!$B$2:$B$501,0)),INDEX('04_PRODUCTOS'!$G$2:$G$501,MATCH(F9,'04_PRODUCTOS'!$B$2:$B$501,0))),INDEX('04_PRODUCTOS'!$E$2:$E$501,MATCH(F9,'04_PRODUCTOS'!$B$2:$B$501,0)))),"") | I9: =IF(AND(G9<>"",H9<>""),G9*H9,"") | J9: =IFERROR(IF(INDEX('04_PRODUCTOS'!$D$2:$D$501,MATCH(F9,'04_PRODUCTOS'!$B$2:$B$501,0))="","",I9-(G9*INDEX('04_PRODUCTOS'!$D$2:$D$501,MATCH(F9,'04_PRODUCTOS'!$B$2:$B$501,0)))),"") | K9: =IF(OR(I9="",J9=""),"",IFERROR(J9/I9,"")) | O9: =IF(D9="","",IFERROR(INDEX('03_CLIENTES'!$A$2:$A$501,MATCH(D9,'03_CLIENTES'!$B$2:$B$501,0)),"")) | P9: =IF(F9="","",IFERROR(INDEX('04_PRODUCTOS'!$A$2:$A$501,MATCH(F9,'04_PRODUCTOS'!$B$2:$B$501,0)),"")) | Q9: =IF(AND(D9<>"",F9<>"",G9>0,H9<>""),IF(O9="","CLIENTE NO ENCONTRADO",IF(P9="","PRODUCTO NO ENCONTRADO","OK")),"")
A10: =IF(OR(D10="",F10=""),"","VEN"&TEXT(ROW()-1,"000000")) | B10: =IF(A10="","",TODAY()) | C10: =IF(A10="","",NOW()) | H10: =IFERROR(IF(E10="Mayorista",IF(INDEX('04_PRODUCTOS'!$F$2:$F$501,MATCH(F10,'04_PRODUCTOS'!$B$2:$B$501,0))="",INDEX('04_PRODUCTOS'!$E$2:$E$501,MATCH(F10,'04_PRODUCTOS'!$B$2:$B$501,0)),INDEX('04_PRODUCTOS'!$F$2:$F$501,MATCH(F10,'04_PRODUCTOS'!$B$2:$B$501,0))),IF(E10="Especial",IF(INDEX('04_PRODUCTOS'!$G$2:$G$501,MATCH(F10,'04_PRODUCTOS'!$B$2:$B$501,0))="",INDEX('04_PRODUCTOS'!$E$2:$E$501,MATCH(F10,'04_PRODUCTOS'!$B$2:$B$501,0)),INDEX('04_PRODUCTOS'!$G$2:$G$501,MATCH(F10,'04_PRODUCTOS'!$B$2:$B$501,0))),INDEX('04_PRODUCTOS'!$E$2:$E$501,MATCH(F10,'04_PRODUCTOS'!$B$2:$B$501,0)))),"") | I10: =IF(AND(G10<>"",H10<>""),G10*H10,"") | J10: =IFERROR(IF(INDEX('04_PRODUCTOS'!$D$2:$D$501,MATCH(F10,'04_PRODUCTOS'!$B$2:$B$501,0))="","",I10-(G10*INDEX('04_PRODUCTOS'!$D$2:$D$501,MATCH(F10,'04_PRODUCTOS'!$B$2:$B$501,0)))),"") | K10: =IF(OR(I10="",J10=""),"",IFERROR(J10/I10,"")) | O10: =IF(D10="","",IFERROR(INDEX('03_CLIENTES'!$A$2:$A$501,MATCH(D10,'03_CLIENTES'!$B$2:$B$501,0)),"")) | P10: =IF(F10="","",IFERROR(INDEX('04_PRODUCTOS'!$A$2:$A$501,MATCH(F10,'04_PRODUCTOS'!$B$2:$B$501,0)),"")) | Q10: =IF(AND(D10<>"",F10<>"",G10>0,H10<>""),IF(O10="","CLIENTE NO ENCONTRADO",IF(P10="","PRODUCTO NO ENCONTRADO","OK")),"")
A11: =IF(OR(D11="",F11=""),"","VEN"&TEXT(ROW()-1,"000000")) | B11: =IF(A11="","",TODAY()) | C11: =IF(A11="","",NOW()) | H11: =IFERROR(IF(E11="Mayorista",IF(INDEX('04_PRODUCTOS'!$F$2:$F$501,MATCH(F11,'04_PRODUCTOS'!$B$2:$B$501,0))="",INDEX('04_PRODUCTOS'!$E$2:$E$501,MATCH(F11,'04_PRODUCTOS'!$B$2:$B$501,0)),INDEX('04_PRODUCTOS'!$F$2:$F$501,MATCH(F11,'04_PRODUCTOS'!$B$2:$B$501,0))),IF(E11="Especial",IF(INDEX('04_PRODUCTOS'!$G$2:$G$501,MATCH(F11,'04_PRODUCTOS'!$B$2:$B$501,0))="",INDEX('04_PRODUCTOS'!$E$2:$E$501,MATCH(F11,'04_PRODUCTOS'!$B$2:$B$501,0)),INDEX('04_PRODUCTOS'!$G$2:$G$501,MATCH(F11,'04_PRODUCTOS'!$B$2:$B$501,0))),INDEX('04_PRODUCTOS'!$E$2:$E$501,MATCH(F11,'04_PRODUCTOS'!$B$2:$B$501,0)))),"") | I11: =IF(AND(G11<>"",H11<>""),G11*H11,"") | J11: =IFERROR(IF(INDEX('04_PRODUCTOS'!$D$2:$D$501,MATCH(F11,'04_PRODUCTOS'!$B$2:$B$501,0))="","",I11-(G11*INDEX('04_PRODUCTOS'!$D$2:$D$501,MATCH(F11,'04_PRODUCTOS'!$B$2:$B$501,0)))),"") | K11: =IF(OR(I11="",J11=""),"",IFERROR(J11/I11,"")) | O11: =IF(D11="","",IFERROR(INDEX('03_CLIENTES'!$A$2:$A$501,MATCH(D11,'03_CLIENTES'!$B$2:$B$501,0)),"")) | P11: =IF(F11="","",IFERROR(INDEX('04_PRODUCTOS'!$A$2:$A$501,MATCH(F11,'04_PRODUCTOS'!$B$2:$B$501,0)),"")) | Q11: =IF(AND(D11<>"",F11<>"",G11>0,H11<>""),IF(O11="","CLIENTE NO ENCONTRADO",IF(P11="","PRODUCTO NO ENCONTRADO","OK")),"")
A12: =IF(OR(D12="",F12=""),"","VEN"&TEXT(ROW()-1,"000000")) | B12: =IF(A12="","",TODAY()) | C12: =IF(A12="","",NOW()) | H12: =IFERROR(IF(E12="Mayorista",IF(INDEX('04_PRODUCTOS'!$F$2:$F$501,MATCH(F12,'04_PRODUCTOS'!$B$2:$B$501,0))="",INDEX('04_PRODUCTOS'!$E$2:$E$501,MATCH(F12,'04_PRODUCTOS'!$B$2:$B$501,0)),INDEX('04_PRODUCTOS'!$F$2:$F$501,MATCH(F12,'04_PRODUCTOS'!$B$2:$B$501,0))),IF(E12="Especial",IF(INDEX('04_PRODUCTOS'!$G$2:$G$501,MATCH(F12,'04_PRODUCTOS'!$B$2:$B$501,0))="",INDEX('04_PRODUCTOS'!$E$2:$E$501,MATCH(F12,'04_PRODUCTOS'!$B$2:$B$501,0)),INDEX('04_PRODUCTOS'!$G$2:$G$501,MATCH(F12,'04_PRODUCTOS'!$B$2:$B$501,0))),INDEX('04_PRODUCTOS'!$E$2:$E$501,MATCH(F12,'04_PRODUCTOS'!$B$2:$B$501,0)))),"") | I12: =IF(AND(G12<>"",H12<>""),G12*H12,"") | J12: =IFERROR(IF(INDEX('04_PRODUCTOS'!$D$2:$D$501,MATCH(F12,'04_PRODUCTOS'!$B$2:$B$501,0))="","",I12-(G12*INDEX('04_PRODUCTOS'!$D$2:$D$501,MATCH(F12,'04_PRODUCTOS'!$B$2:$B$501,0)))),"") | K12: =IF(OR(I12="",J12=""),"",IFERROR(J12/I12,"")) | O12: =IF(D12="","",IFERROR(INDEX('03_CLIENTES'!$A$2:$A$501,MATCH(D12,'03_CLIENTES'!$B$2:$B$501,0)),"")) | P12: =IF(F12="","",IFERROR(INDEX('04_PRODUCTOS'!$A$2:$A$501,MATCH(F12,'04_PRODUCTOS'!$B$2:$B$501,0)),"")) | Q12: =IF(AND(D12<>"",F12<>"",G12>0,H12<>""),IF(O12="","CLIENTE NO ENCONTRADO",IF(P12="","PRODUCTO NO ENCONTRADO","OK")),"")
A13: =IF(OR(D13="",F13=""),"","VEN"&TEXT(ROW()-1,"000000")) | B13: =IF(A13="","",TODAY()) | C13: =IF(A13="","",NOW()) | H13: =IFERROR(IF(E13="Mayorista",IF(INDEX('04_PRODUCTOS'!$F$2:$F$501,MATCH(F13,'04_PRODUCTOS'!$B$2:$B$501,0))="",INDEX('04_PRODUCTOS'!$E$2:$E$501,MATCH(F13,'04_PRODUCTOS'!$B$2:$B$501,0)),INDEX('04_PRODUCTOS'!$F$2:$F$501,MATCH(F13,'04_PRODUCTOS'!$B$2:$B$501,0))),IF(E13="Especial",IF(INDEX('04_PRODUCTOS'!$G$2:$G$501,MATCH(F13,'04_PRODUCTOS'!$B$2:$B$501,0))="",INDEX('04_PRODUCTOS'!$E$2:$E$501,MATCH(F13,'04_PRODUCTOS'!$B$2:$B$501,0)),INDEX('04_PRODUCTOS'!$G$2:$G$501,MATCH(F13,'04_PRODUCTOS'!$B$2:$B$501,0))),INDEX('04_PRODUCTOS'!$E$2:$E$501,MATCH(F13,'04_PRODUCTOS'!$B$2:$B$501,0)))),"") | I13: =IF(AND(G13<>"",H13<>""),G13*H13,"") | J13: =IFERROR(IF(INDEX('04_PRODUCTOS'!$D$2:$D$501,MATCH(F13,'04_PRODUCTOS'!$B$2:$B$501,0))="","",I13-(G13*INDEX('04_PRODUCTOS'!$D$2:$D$501,MATCH(F13,'04_PRODUCTOS'!$B$2:$B$501,0)))),"") | K13: =IF(OR(I13="",J13=""),"",IFERROR(J13/I13,"")) | O13: =IF(D13="","",IFERROR(INDEX('03_CLIENTES'!$A$2:$A$501,MATCH(D13,'03_CLIENTES'!$B$2:$B$501,0)),"")) | P13: =IF(F13="","",IFERROR(INDEX('04_PRODUCTOS'!$A$2:$A$501,MATCH(F13,'04_PRODUCTOS'!$B$2:$B$501,0)),"")) | Q13: =IF(AND(D13<>"",F13<>"",G13>0,H13<>""),IF(O13="","CLIENTE NO ENCONTRADO",IF(P13="","PRODUCTO NO ENCONTRADO","OK")),"")
... A500: =IF(OR(D500="",F500=""),"","VEN"&TEXT(ROW()-1,"000000")) | B500: =IF(A500="","",TODAY()) | C500: =IF(A500="","",NOW()) | H500: =IFERROR(IF(E500="Mayorista",IF(INDEX('04_PRODUCTOS'!$F$2:$F$501,MATCH(F500,'04_PRODUCTOS'!$B$2:$B$501,0))="",INDEX('04_PRODUCTOS'!$E$2:$E$501,MATCH(F500,'04_PRODUCTOS'!$B$2:$B$501,0)),INDEX('04_PRODUCTOS'!$F$2:$F$501,MATCH(F500,'04_PRODUCTOS'!$B$2:$B$501,0))),IF(E500="Especial",IF(INDEX('04_PRODUCTOS'!$G$2:$G$501,MATCH(F500,'04_PRODUCTOS'!$B$2:$B$501,0))="",INDEX('04_PRODUCTOS'!$E$2:$E$501,MATCH(F500,'04_PRODUCTOS'!$B$2:$B$501,0)),INDEX('04_PRODUCTOS'!$G$2:$G$501,MATCH(F500,'04_PRODUCTOS'!$B$2:$B$501,0))),INDEX('04_PRODUCTOS'!$E$2:$E$501,MATCH(F500,'04_PRODUCTOS'!$B$2:$B$501,0)))),"") | I500: =IF(AND(G500<>"",H500<>""),G500*H500,"") | J500: =IFERROR(IF(INDEX('04_PRODUCTOS'!$D$2:$D$501,MATCH(F500,'04_PRODUCTOS'!$B$2:$B$501,0))="","",I500-(G500*INDEX('04_PRODUCTOS'!$D$2:$D$501,MATCH(F500,'04_PRODUCTOS'!$B$2:$B$501,0)))),"") | K500: =IF(OR(I500="",J500=""),"",IFERROR(J500/I500,"")) | O500: =IF(D500="","",IFERROR(INDEX('03_CLIENTES'!$A$2:$A$501,MATCH(D500,'03_CLIENTES'!$B$2:$B$501,0)),"")) | P500: =IF(F500="","",IFERROR(INDEX('04_PRODUCTOS'!$A$2:$A$501,MATCH(F500,'04_PRODUCTOS'!$B$2:$B$501,0)),"")) | Q500: =IF(AND(D500<>"",F500<>"",G500>0,H500<>""),IF(O500="","CLIENTE NO ENCONTRADO",IF(P500="","PRODUCTO NO ENCONTRADO","OK")),"")

Sheet 06_TICKET

Sheet 07_CAJA

Sheet 08_STOCK

Sheet 09_CTACTE

Sheet 10_DASHBOARD
A1: CARNE PREMIUM ERP - DASHBOARD OPERATIVO
A3: Ventas registradas | B3: =COUNTIF('05_VENTAS'!$A$2:$A$501,"<>") -> 499
A4: Facturación | B4: =SUM('05_VENTAS'!$I$2:$I$501) -> 0
A5: Ganancia | B5: =SUM('05_VENTAS'!$J$2:$J$501) -> 0
A6: Margen | B6: =IFERROR(B5/B4,"")
A7: Kg vendidos | B7: =SUM('05_VENTAS'!$G$2:$G$501) -> 0
A8: Ticket promedio | B8: =IFERROR(B4/B3,"") -> 0
A9: Ventas con error | B9: =COUNTIF('05_VENTAS'!$Q$2:$Q$501,"<>OK")-COUNTIF('05_VENTAS'!$Q$2:$Q$501,"") -> 0

Sheet 11_AUDITORIA

Sheet 12_VERSION
A1: Campo | B1: Valor
A2: Versión | B2: 0.1.5
A3: Build | B3: MVP 0.1.5 - Ofertas automáticas en Ventas
A4: Estado | B4: Generado y validado
A5: BuildToken | B5: 0.1.5-20260902195723
A6: Generado | B6: 2026-09-02T19:23:16

Sheet 13_LOG
A1: Fecha | B1: Versión | C1: Acción | D1: Detalle
A2: 46260.817 | B2: 0.1.1 | C2: BUILD | D2: 0.1.1-20260826-193631-64b74852
A3: 46260.83 | B3: 0.1.1 | C3: BUILD | D3: 0.1.1-20260826-195455-7d9ebd26
A4: 46265.453 | B4: 0.1.2 | C4: BUILD | D4: 0.1.2-20260831-105229-c07138aa
A5: 46265.456 | B5: 0.1.2 | C5: BUILD | D5: 0.1.2-20260831-105716-f5bbeaf2
A6: 46266.485 | B6: 0.1.2 | C6: BUILD | D6: 0.1.2-20260901-113839-61339b82
A7: 46266.491 | B7: 0.1.5 | C7: BUILD | D7: 0.1.5-20260901-114643-93592eee
A8: 46267.808 | B8: 0.1.5 | C8: BUILD | D8: 0.1.5-20260902-192316-28e5886b

Sheet 23_OFERTAS
A1: OfertaID | B1: ProductoID | C1: Producto | D1: NombreOferta | E1: PrecioOferta | F1: Descuento% | G1: FechaInicio | H1: FechaFin | I1: MinKg | J1: Estado | K1: Prioridad
